icsk/__init__.py
icsk/crypto/__init__.py
icsk/crypto/base.py
icsk/crypto/decoder.py
icsk/crypto/encoder.py
ichisaki-0.0.8.dist-info/LICENSE
ichisaki-0.0.8.dist-info/METADATA
ichisaki-0.0.8.dist-info/WHEEL
ichisaki-0.0.8.dist-info/top_level.txt
ichisaki-0.0.8.dist-info/RECORD
