Metadata-Version: 2.1
Name: ichisaki
Version: 0.0.8
Summary: A Simple Toolkit just for FUN
Home-page: https://github.com/sandyzikun/ichisaki.git
License: UNKNOWN
Platform: UNKNOWN
Classifier: Programming Language :: Python :: 3
Classifier: License :: OSI Approved :: GNU General Public License v3 (GPLv3)
License-File: LICENSE
Requires-Dist: numpy (>=1.14.3)
